LICENSE
README.md
setup.py
trademaster409/__init__.py
trademaster409.egg-info/PKG-INFO
trademaster409.egg-info/SOURCES.txt
trademaster409.egg-info/dependency_links.txt
trademaster409.egg-info/top_level.txt
trademaster409/agents/__init__.py
trademaster409/agents/builder.py
trademaster409/agents/custom.py
trademaster409/agents/algorithmic_trading/__init__.py
trademaster409/agents/algorithmic_trading/dqn.py
trademaster409/agents/high_frequency_trading/__init__.py
trademaster409/agents/high_frequency_trading/ddqn.py
trademaster409/agents/order_execution/__init__.py
trademaster409/agents/order_execution/eteo.py
trademaster409/agents/order_execution/pd.py
trademaster409/agents/portfolio_management/__init__.py
trademaster409/agents/portfolio_management/deeptrader.py
trademaster409/agents/portfolio_management/eiie.py
trademaster409/agents/portfolio_management/investor_imitator.py
trademaster409/collector/__init__.py
trademaster409/collector/binance.py
trademaster409/collector/builder.py
trademaster409/collector/custom.py
trademaster409/collector/helper/__init__.py
trademaster409/collector/helper/celery_app.py
trademaster409/collector/helper/celery_config.py
trademaster409/collector/helper/pika_connection.py
trademaster409/collector/helper/run_celery.py
trademaster409/collector/helper/websocket_consumer.py
trademaster409/collector/helper/websocket_producer.py
trademaster409/datasets/__init__.py
trademaster409/datasets/builder.py
trademaster409/datasets/custom.py
trademaster409/datasets/algorithmic_trading/__init__.py
trademaster409/datasets/algorithmic_trading/dataset.py
trademaster409/datasets/high_frequency_trading/__init__.py
trademaster409/datasets/high_frequency_trading/dataset.py
trademaster409/datasets/order_execution/__init__.py
trademaster409/datasets/order_execution/dataset.py
trademaster409/datasets/portfolio_management/__init__.py
trademaster409/datasets/portfolio_management/dataset.py
trademaster409/environments/__init__.py
trademaster409/environments/builder.py
trademaster409/environments/custom.py
trademaster409/environments/algorithmic_trading/__init__.py
